<?xml version="1.0" encoding="UTF-8" standalone="yes"?>
<data-set xmlns:xsi="http://www.w3.org/2001/XMLSchema-instance">
	<record>
		<C>4Y369</C>
		<Link>/cgi/rws5.pl?FORM=EFS_UNIV_SP14&amp;M=BS Aerospace Engineering&amp;N=Justin Gnant&amp;Y=2009-10&amp;L=DB&amp;C=4Y369</Link>
	</record>
	<record>
		<C>4Y103</C>
		<Link>/cgi/rws5.pl?FORM=EFS_UNIV_SP14&amp;M=BS Aerospace Engineering&amp;N=Montgomery Kirk&amp;Y=2009-10&amp;L=DB&amp;C=4Y103</Link>
	</record>
	<record>
		<C>4Y276</C>
		<Link>/cgi/rws5.pl?FORM=EFS_UNIV_SP14&amp;M=BS Aerospace Engineering&amp;N=Brad Couto&amp;Y=2009-10&amp;L=DB&amp;C=4Y276</Link>
	</record>
	<record>
		<C>4Y5</C>
		<Link>/cgi/rws5.pl?FORM=EFS_UNIV_SP14&amp;M=BS Aerospace Engineering&amp;N=Hesham Afifi&amp;Y=2009-10&amp;L=DB&amp;C=4Y5</Link>
	</record>
	<record>
		<C>4Y47</C>
		<Link>/cgi/rws5.pl?FORM=EFS_UNIV_SP14&amp;M=BS Aerospace Engineering&amp;N=Emily Vanderwal&amp;Y=2009-10&amp;L=DB&amp;C=4Y47</Link>
	</record>
	<record>
		<C>4Y171</C>
		<Link>/cgi/rws5.pl?FORM=EFS_UNIV_SP14&amp;M=BS Aerospace Engineering&amp;N=Adam Marcucci&amp;Y=2009-10&amp;L=DB&amp;C=4Y171</Link>
	</record>
	<record>
		<C>4Y96</C>
		<Link>/cgi/rws5.pl?FORM=EFS_UNIV_SP14&amp;M=BS Aerospace Engineering&amp;N=Geoffrey Licciardello&amp;Y=2009-10&amp;L=DB&amp;C=4Y96</Link>
	</record>
	<record>
		<C>4Y108</C>
		<Link>/cgi/rws5.pl?FORM=EFS_UNIV_SP14&amp;M=BS Aerospace Engineering&amp;N=Jillian Eaton&amp;Y=2009-10&amp;L=DB&amp;C=4Y108</Link>
	</record>
	<record>
		<C>4Y174</C>
		<Link>/cgi/rws5.pl?FORM=EFS_UNIV_SP14&amp;M=BS Aerospace Engineering&amp;N=Benjamin Tegge&amp;Y=2009-10&amp;L=DB&amp;C=4Y174</Link>
	</record>
	<record>
		<C>4Y58</C>
		<Link>/cgi/rws5.pl?FORM=EFS_UNIV_SP14&amp;M=BS Aerospace Engineering&amp;N=Dwight De Carme&amp;Y=2009-10&amp;L=DB&amp;C=4Y58</Link>
	</record>
	<record>
		<C>4Y95</C>
		<Link>/cgi/rws5.pl?FORM=EFS_UNIV_SP14&amp;M=BS Engineering Physics&amp;N=Nika Stephens&amp;Y=2009-10&amp;L=DB&amp;C=4Y95</Link>
	</record>
	<record>
		<C>4Y339</C>
		<Link>/cgi/rws5.pl?FORM=EFS_UNIV_SP14&amp;M=BS Software Engineering&amp;N=Venu Madhabhushanam&amp;Y=2009-10&amp;L=DB&amp;C=4Y339</Link>
	</record>
	<record>
		<C>4Y236</C>
		<Link>/cgi/rws5.pl?FORM=EFS_UNIV_SP14&amp;M=BS Software Engineering&amp;N=Philip Kunz&amp;Y=2009-10&amp;L=DB&amp;C=4Y236</Link>
	</record>
	<record>
		<C>217</C>
		<Link>/cgi/rws5.pl?FORM=EFS_UNIV_SP14&amp;M=BS Aeronautical Science&amp;N=Derek Herchko&amp;Y=2011-12&amp;L=DB&amp;C=217</Link>
	</record>
	<record>
		<C>379</C>
		<Link>/cgi/rws5.pl?FORM=EFS_UNIV_SP14&amp;M=BS Aeronautical Science&amp;N=Adam Flowers&amp;Y=2011-12&amp;L=DB&amp;C=379</Link>
	</record>
	<record>
		<C>439</C>
		<Link>/cgi/rws5.pl?FORM=EFS_UNIV_SP14&amp;M=BS Aeronautical Science&amp;N=Daniel Kearney&amp;Y=2011-12&amp;L=DB&amp;C=439</Link>
	</record>
	<record>
		<C>604</C>
		<Link>/cgi/rws5.pl?FORM=EFS_UNIV_SP14&amp;M=BS Aeronautical Science&amp;N=Cameron McCune&amp;Y=2011-12&amp;L=DB&amp;C=604</Link>
	</record>
	<record>
		<C>627</C>
		<Link>/cgi/rws5.pl?FORM=EFS_UNIV_SP14&amp;M=BS Aeronautical Science&amp;N=Ryan Lowrey&amp;Y=2011-12&amp;L=DB&amp;C=627</Link>
	</record>
	<record>
		<C>130</C>
		<Link>/cgi/rws5.pl?FORM=EFS_UNIV_SP14&amp;M=BS Aeronautics&amp;N=Jordan La Motte&amp;Y=2011-12&amp;L=DB&amp;C=130</Link>
	</record>
	<record>
		<C>454</C>
		<Link>/cgi/rws5.pl?FORM=EFS_UNIV_SP14&amp;M=BS Aeronautics&amp;N=Andrew Wyka&amp;Y=2011-12&amp;L=DB&amp;C=454</Link>
	</record>
	<record>
		<C>616</C>
		<Link>/cgi/rws5.pl?FORM=EFS_UNIV_SP14&amp;M=BS Aeronautics&amp;N=Brayden Hardesty&amp;Y=2011-12&amp;L=DB&amp;C=616</Link>
	</record>
	<record>
		<C>1066</C>
		<Link>/cgi/rws5.pl?FORM=EFS_UNIV_SP14&amp;M=BS Aeronautics&amp;N=Gathan Broadus&amp;Y=2011-12&amp;L=DB&amp;C=1066</Link>
	</record>
	<record>
		<C>64</C>
		<Link>/cgi/rws5.pl?FORM=EFS_UNIV_SP14&amp;M=BS Aerospace Engineering&amp;N=Benjamin Breitberg&amp;Y=2011-12&amp;L=DB&amp;C=64</Link>
	</record>
	<record>
		<C>106</C>
		<Link>/cgi/rws5.pl?FORM=EFS_UNIV_SP14&amp;M=BS Aerospace Engineering&amp;N=Victor Nazario&amp;Y=2011-12&amp;L=DB&amp;C=106</Link>
	</record>
	<record>
		<C>178</C>
		<Link>/cgi/rws5.pl?FORM=EFS_UNIV_SP14&amp;M=BS Aerospace Engineering&amp;N=Dennis Lautenschuetz&amp;Y=2011-12&amp;L=DB&amp;C=178</Link>
	</record>
	<record>
		<C>333</C>
		<Link>/cgi/rws5.pl?FORM=EFS_UNIV_SP14&amp;M=BS Aerospace Engineering&amp;N=Jorge Pantoja&amp;Y=2011-12&amp;L=DB&amp;C=333</Link>
	</record>
	<record>
		<C>363</C>
		<Link>/cgi/rws5.pl?FORM=EFS_UNIV_SP14&amp;M=BS Aerospace Engineering&amp;N=Timothy Huber&amp;Y=2011-12&amp;L=DB&amp;C=363</Link>
	</record>
	<record>
		<C>394</C>
		<Link>/cgi/rws5.pl?FORM=EFS_UNIV_SP14&amp;M=BS Aerospace Engineering&amp;N=Franklin Ogden&amp;Y=2011-12&amp;L=DB&amp;C=394</Link>
	</record>
	<record>
		<C>411</C>
		<Link>/cgi/rws5.pl?FORM=EFS_UNIV_SP14&amp;M=BS Aerospace Engineering&amp;N=Randall Pauley&amp;Y=2011-12&amp;L=DB&amp;C=411</Link>
	</record>
	<record>
		<C>710</C>
		<Link>/cgi/rws5.pl?FORM=EFS_UNIV_SP14&amp;M=BS Aerospace Engineering&amp;N=Siddharth Menon&amp;Y=2011-12&amp;L=DB&amp;C=710</Link>
	</record>
	<record>
		<C>770</C>
		<Link>/cgi/rws5.pl?FORM=EFS_UNIV_SP14&amp;M=BS Aerospace Engineering&amp;N=Georgios Angelidis&amp;Y=2011-12&amp;L=DB&amp;C=770</Link>
	</record>
	<record>
		<C>787</C>
		<Link>/cgi/rws5.pl?FORM=EFS_UNIV_SP14&amp;M=BS Aerospace Engineering&amp;N=Alexander Salimian&amp;Y=2011-12&amp;L=DB&amp;C=787</Link>
	</record>
	<record>
		<C>799</C>
		<Link>/cgi/rws5.pl?FORM=EFS_UNIV_SP14&amp;M=BS Aerospace Engineering&amp;N=Stephanie Lepchenske&amp;Y=2011-12&amp;L=DB&amp;C=799</Link>
	</record>
	<record>
		<C>972</C>
		<Link>/cgi/rws5.pl?FORM=EFS_UNIV_SP14&amp;M=BS Aerospace Engineering&amp;N=Nishantha Wimalarathna&amp;Y=2011-12&amp;L=DB&amp;C=972</Link>
	</record>
	<record>
		<C>5</C>
		<Link>/cgi/rws5.pl?FORM=EFS_UNIV_SP14&amp;M=BS Air Traffic Management&amp;N=Nathaniel Parker&amp;Y=2011-12&amp;L=DB&amp;C=5</Link>
	</record>
	<record>
		<C>192</C>
		<Link>/cgi/rws5.pl?FORM=EFS_UNIV_SP14&amp;M=BS Air Traffic Management&amp;N=Rebecca Wood&amp;Y=2011-12&amp;L=DB&amp;C=192</Link>
	</record>
	<record>
		<C>284</C>
		<Link>/cgi/rws5.pl?FORM=EFS_UNIV_SP14&amp;M=BS Air Traffic Management&amp;N=Phillip Gable&amp;Y=2011-12&amp;L=DB&amp;C=284</Link>
	</record>
	<record>
		<C>434</C>
		<Link>/cgi/rws5.pl?FORM=EFS_UNIV_SP14&amp;M=BS Air Traffic Management&amp;N=James Scott&amp;Y=2011-12&amp;L=DB&amp;C=434</Link>
	</record>
	<record>
		<C>600</C>
		<Link>/cgi/rws5.pl?FORM=EFS_UNIV_SP14&amp;M=BS Air Traffic Management&amp;N=Alyssa Smith&amp;Y=2011-12&amp;L=DB&amp;C=600</Link>
	</record>
	<record>
		<C>942</C>
		<Link>/cgi/rws5.pl?FORM=EFS_UNIV_SP14&amp;M=BS Air Traffic Management&amp;N=Danielle Murray&amp;Y=2011-12&amp;L=DB&amp;C=942</Link>
	</record>
	<record>
		<C>1091</C>
		<Link>/cgi/rws5.pl?FORM=EFS_UNIV_SP14&amp;M=BS Air Traffic Management&amp;N=Camila Sampaio&amp;Y=2011-12&amp;L=DB&amp;C=1091</Link>
	</record>
	<record>
		<C>618</C>
		<Link>/cgi/rws5.pl?FORM=EFS_UNIV_SP14&amp;M=BS Aviation Business Administration&amp;N=Matthias Klatt&amp;Y=2011-12&amp;L=DB&amp;C=618</Link>
	</record>
	<record>
		<C>599</C>
		<Link>/cgi/rws5.pl?FORM=EFS_UNIV_SP14&amp;M=BS Aviation Maintenance Science&amp;N=Taekyu Lee&amp;Y=2011-12&amp;L=DB&amp;C=599</Link>
	</record>
	<record>
		<C>871</C>
		<Link>/cgi/rws5.pl?FORM=EFS_UNIV_SP14&amp;M=BS Aviation Maintenance Science&amp;N=Deep Lad&amp;Y=2011-12&amp;L=DB&amp;C=871</Link>
	</record>
	<record>
		<C>670</C>
		<Link>/cgi/rws5.pl?FORM=EFS_UNIV_SP14&amp;M=BS Aviation Management&amp;N=Devon Weinman&amp;Y=2011-12&amp;L=DB&amp;C=670</Link>
	</record>
	<record>
		<C>11</C>
		<Link>/cgi/rws5.pl?FORM=EFS_UNIV_SP14&amp;M=BS Business Administration&amp;N=Joe Williams&amp;Y=2011-12&amp;L=DB&amp;C=11</Link>
	</record>
	<record>
		<C>410</C>
		<Link>/cgi/rws5.pl?FORM=EFS_UNIV_SP14&amp;M=BS Business Administration&amp;N=Michael Groseclose&amp;Y=2011-12&amp;L=DB&amp;C=410</Link>
	</record>
	<record>
		<C>1093</C>
		<Link>/cgi/rws5.pl?FORM=EFS_UNIV_SP14&amp;M=BS Communication&amp;N=Nina Kontrec&amp;Y=2011-12&amp;L=DB&amp;C=1093</Link>
	</record>
	<record>
		<C>1097</C>
		<Link>/cgi/rws5.pl?FORM=EFS_UNIV_SP14&amp;M=BS Homeland Security&amp;N=James Sherman&amp;Y=2011-12&amp;L=DB&amp;C=1097</Link>
	</record>
	<record>
		<C>1086</C>
		<Link>/cgi/rws5.pl?FORM=EFS_UNIV_SP14&amp;M=BS Mechanical Engineering&amp;N=Kelly Burkholder&amp;Y=2011-12&amp;L=DB&amp;C=1086</Link>
	</record>
	<record>
		<C>340</C>
		<Link>/cgi/rws5.pl?FORM=EFS_UNIV_SP14&amp;M=BS Safety Science&amp;N=Joseph Hendges&amp;Y=2011-12&amp;L=DB&amp;C=340</Link>
	</record>
	<record>
		<C>817</C>
		<Link>/cgi/rws5.pl?FORM=EFS_UNIV_SP14&amp;M=BS Safety Science&amp;N=Frank Diaz&amp;Y=2011-12&amp;L=DB&amp;C=817</Link>
	</record>
	<record>
		<C>649</C>
		<Link>/cgi/rws5.pl?FORM=EFS_UNIV_SP14&amp;M=M Business Admin&amp;N=George Ray&amp;Y=2011-12&amp;L=DB&amp;C=649</Link>
	</record>
	<record>
		<C>1083</C>
		<Link>/cgi/rws5.pl?FORM=EFS_UNIV_SP14&amp;M=M Business Admin&amp;N=Arti Singh&amp;Y=2011-12&amp;L=DB&amp;C=1083</Link>
	</record>
	<record>
		<C>1052</C>
		<Link>/cgi/rws5.pl?FORM=EFS_UNIV_SP14&amp;M=M Software Engineering&amp;N=Bapu Hirave&amp;Y=2011-12&amp;L=DB&amp;C=1052</Link>
	</record>
	<record>
		<C>918</C>
		<Link>/cgi/rws5.pl?FORM=EFS_UNIV_SP14&amp;M=M-MS Aerospace Engineering&amp;N=Charles Grivotet&amp;Y=2011-12&amp;L=DB&amp;C=918</Link>
	</record>
	<record>
		<C>8</C>
		<Link>/cgi/rws5.pl?FORM=EFS_UNIV_SP14&amp;M=MS Aeronautics&amp;N=Hugh Belle&amp;Y=2011-12&amp;L=DB&amp;C=8</Link>
	</record>
	<record>
		<C>51</C>
		<Link>/cgi/rws5.pl?FORM=EFS_UNIV_SP14&amp;M=MS Aeronautics&amp;N=Maciej Majewski&amp;Y=2011-12&amp;L=DB&amp;C=51</Link>
	</record>
	<record>
		<C>989</C>
		<Link>/cgi/rws5.pl?FORM=EFS_UNIV_SP14&amp;M=MS Human Factors &amp; Systems&amp;N=Robert Brown&amp;Y=2011-12&amp;L=DB&amp;C=989</Link>
	</record>
	<record>
		<C>537</C>
		<Link>/cgi/rws5.pl?FORM=EFS_UNIV_SP14&amp;M=MS Human Factors &amp; Systems&amp;N=Abigail Gaston&amp;Y=2011-12&amp;L=DB&amp;C=537</Link>
	</record>
	<record>
		<C>899</C>
		<Link>/cgi/rws5.pl?FORM=EFS_UNIV_SP14&amp;M=BS Aeronautical Science&amp;N=Michelle Lam&amp;Y=2011-12&amp;L=PC&amp;C=899</Link>
	</record>
	<record>
		<C>966</C>
		<Link>/cgi/rws5.pl?FORM=EFS_UNIV_SP14&amp;M=BS Aeronautical Science&amp;N=Lynden Vazquez-Tompkins&amp;Y=2011-12&amp;L=PC&amp;C=966</Link>
	</record>
	<record>
		<C>619</C>
		<Link>/cgi/rws5.pl?FORM=EFS_UNIV_SP14&amp;M=BS Aeronautical Science&amp;N=Andrew Cochran&amp;Y=2011-12&amp;L=PC&amp;C=619</Link>
	</record>
	<record>
		<C>378</C>
		<Link>/cgi/rws5.pl?FORM=EFS_UNIV_SP14&amp;M=BS Aeronautical Science&amp;N=Taylor Allen&amp;Y=2011-12&amp;L=PC&amp;C=378</Link>
	</record>
	<record>
		<C>701</C>
		<Link>/cgi/rws5.pl?FORM=EFS_UNIV_SP14&amp;M=BS Aeronautical Science&amp;N=Stephen Hamacher&amp;Y=2011-12&amp;L=PC&amp;C=701</Link>
	</record>
	<record>
		<C>702</C>
		<Link>/cgi/rws5.pl?FORM=EFS_UNIV_SP14&amp;M=BS Aeronautical Science&amp;N=Cody Hart&amp;Y=2011-12&amp;L=PC&amp;C=702</Link>
	</record>
	<record>
		<C>521</C>
		<Link>/cgi/rws5.pl?FORM=EFS_UNIV_SP14&amp;M=BS Aeronautical Science&amp;N=Jacob Theander&amp;Y=2011-12&amp;L=PC&amp;C=521</Link>
	</record>
	<record>
		<C>30</C>
		<Link>/cgi/rws5.pl?FORM=EFS_UNIV_SP14&amp;M=BS Aeronautics&amp;N=Kyle Roth&amp;Y=2011-12&amp;L=PC&amp;C=30</Link>
	</record>
	<record>
		<C>566</C>
		<Link>/cgi/rws5.pl?FORM=EFS_UNIV_SP14&amp;M=BS Aeronautics&amp;N=Laura Clark&amp;Y=2011-12&amp;L=PC&amp;C=566</Link>
	</record>
	<record>
		<C>933</C>
		<Link>/cgi/rws5.pl?FORM=EFS_UNIV_SP14&amp;M=BS Aerospace Engineering&amp;N=Frazier Biba&amp;Y=2011-12&amp;L=PC&amp;C=933</Link>
	</record>
	<record>
		<C>111</C>
		<Link>/cgi/rws5.pl?FORM=EFS_UNIV_SP14&amp;M=BS Aerospace Engineering&amp;N=Allison Buss&amp;Y=2011-12&amp;L=PC&amp;C=111</Link>
	</record>
	<record>
		<C>299</C>
		<Link>/cgi/rws5.pl?FORM=EFS_UNIV_SP14&amp;M=BS Aerospace Engineering&amp;N=Christopher Morrison&amp;Y=2011-12&amp;L=PC&amp;C=299</Link>
	</record>
	<record>
		<C>846</C>
		<Link>/cgi/rws5.pl?FORM=EFS_UNIV_SP14&amp;M=BS Aerospace Engineering&amp;N=Nicholas Mondo&amp;Y=2011-12&amp;L=PC&amp;C=846</Link>
	</record>
	<record>
		<C>505</C>
		<Link>/cgi/rws5.pl?FORM=EFS_UNIV_SP14&amp;M=BS Aerospace Engineering&amp;N=George Somi&amp;Y=2011-12&amp;L=PC&amp;C=505</Link>
	</record>
	<record>
		<C>591</C>
		<Link>/cgi/rws5.pl?FORM=EFS_UNIV_SP14&amp;M=BS Applied Meteorology&amp;N=Trevis Matheus&amp;Y=2011-12&amp;L=PC&amp;C=591</Link>
	</record>
	<record>
		<C>266</C>
		<Link>/cgi/rws5.pl?FORM=EFS_UNIV_SP14&amp;M=BS Aviation Business Administration&amp;N=Taylor Brennan&amp;Y=2011-12&amp;L=PC&amp;C=266</Link>
	</record>
	<record>
		<C>1119</C>
		<Link>/cgi/rws5.pl?FORM=EFS_UNIV_SP14&amp;M=BS Aviation Business Administration&amp;N=Brandon Scott&amp;Y=2011-12&amp;L=PC&amp;C=1119</Link>
	</record>
	<record>
		<C>451</C>
		<Link>/cgi/rws5.pl?FORM=EFS_UNIV_SP14&amp;M=BS Aviation Business Administration&amp;N=Danielle Schnake&amp;Y=2011-12&amp;L=PC&amp;C=451</Link>
	</record>
	<record>
		<C>697</C>
		<Link>/cgi/rws5.pl?FORM=EFS_UNIV_SP14&amp;M=BS Computer Engineering&amp;N=Joshua Hansen&amp;Y=2011-12&amp;L=PC&amp;C=697</Link>
	</record>
	<record>
		<C>334</C>
		<Link>/cgi/rws5.pl?FORM=EFS_UNIV_SP14&amp;M=BS Computer Engineering&amp;N=Timothy Lemm&amp;Y=2011-12&amp;L=PC&amp;C=334</Link>
	</record>
	<record>
		<C>970</C>
		<Link>/cgi/rws5.pl?FORM=EFS_UNIV_SP14&amp;M=BS Computer Engineering&amp;N=Joshua Gavroy&amp;Y=2011-12&amp;L=PC&amp;C=970</Link>
	</record>
	<record>
		<C>955</C>
		<Link>/cgi/rws5.pl?FORM=EFS_UNIV_SP14&amp;M=BS Computer Engineering&amp;N=Logan Hennessy&amp;Y=2011-12&amp;L=PC&amp;C=955</Link>
	</record>
	<record>
		<C>226</C>
		<Link>/cgi/rws5.pl?FORM=EFS_UNIV_SP14&amp;M=BS Global Security and Intelligence Studies&amp;N=Jason Thatcher&amp;Y=2011-12&amp;L=PC&amp;C=226</Link>
	</record>
	<record>
		<C>499</C>
		<Link>/cgi/rws5.pl?FORM=EFS_UNIV_SP14&amp;M=BS Global Security and Intelligence Studies&amp;N=Charles Vitellaro&amp;Y=2011-12&amp;L=PC&amp;C=499</Link>
	</record>
	<record>
		<C>740</C>
		<Link>/cgi/rws5.pl?FORM=EFS_UNIV_SP14&amp;M=BS Global Security and Intelligence Studies&amp;N=Ashley Mully&amp;Y=2011-12&amp;L=PC&amp;C=740</Link>
	</record>
	<record>
		<C>744</C>
		<Link>/cgi/rws5.pl?FORM=EFS_UNIV_SP14&amp;M=BS Interdisciplinary / Aerospace Studies&amp;N=Dominic Shababy&amp;Y=2011-12&amp;L=PC&amp;C=744</Link>
	</record>
	<record>
		<C>4Y245</C>
		<Link>/cgi/rws5.pl?FORM=EFS_UNIV_SP14&amp;M=BS Aerospace Engineering&amp;N=Dylan Cragg&amp;Y=2009-10&amp;L=PC&amp;C=4Y245</Link>
	</record>
	<record>
		<C>4Y189</C>
		<Link>/cgi/rws5.pl?FORM=EFS_UNIV_SP14&amp;M=BS Aerospace Engineering&amp;N=Kali Schroeder&amp;Y=2009-10&amp;L=PC&amp;C=4Y189</Link>
	</record>
	<record>
		<C>4Y287</C>
		<Link>/cgi/rws5.pl?FORM=EFS_UNIV_SP14&amp;M=BS Aerospace Engineering&amp;N=Charles Schnake&amp;Y=2009-10&amp;L=PC&amp;C=4Y287</Link>
	</record>
	<record>
		<C>4Y152</C>
		<Link>/cgi/rws5.pl?FORM=EFS_UNIV_SP14&amp;M=BS Aerospace Engineering&amp;N=Kennith Bowen&amp;Y=2009-10&amp;L=PC&amp;C=4Y152</Link>
	</record>
	<record>
		<C>4Y238</C>
		<Link>/cgi/rws5.pl?FORM=EFS_UNIV_SP14&amp;M=BS Aerospace Engineering&amp;N=Kyle Wright&amp;Y=2009-10&amp;L=PC&amp;C=4Y238</Link>
	</record>
	<record>
		<C>4Y86</C>
		<Link>/cgi/rws5.pl?FORM=EFS_UNIV_SP14&amp;M=BS Aerospace Engineering&amp;N=Kyle Arcurio&amp;Y=2009-10&amp;L=PC&amp;C=4Y86</Link>
	</record>
	<record>
		<C>4Y4</C>
		<Link>/cgi/rws5.pl?FORM=EFS_UNIV_SP14&amp;M=BS Aerospace Engineering&amp;N=Douglas Ballash&amp;Y=2009-10&amp;L=PC&amp;C=4Y4</Link>
	</record>
	<record>
		<C>4Y6</C>
		<Link>/cgi/rws5.pl?FORM=EFS_UNIV_SP14&amp;M=BS Aerospace Engineering&amp;N=Brandon Lanktree&amp;Y=2009-10&amp;L=PC&amp;C=4Y6</Link>
	</record>
	<record>
		<C>4Y289</C>
		<Link>/cgi/rws5.pl?FORM=EFS_UNIV_SP14&amp;M=BS Aerospace Engineering&amp;N=Nicholas Hammons&amp;Y=2009-10&amp;L=PC&amp;C=4Y289</Link>
	</record>
</data-set>